{
	"name": "DestinationDataset_b3b",
	"properties": {
		"linkedServiceName": {
			"referenceName": "AzureSqlDatabase1",
			"type": "LinkedServiceReference"
		},
		"annotations": [],
		"type": "AzureSqlTable",
		"schema": [
			{
				"name": "BookingID",
				"type": "varchar",
				"precision": 0,
				"scale": 0
			},
			{
				"name": "HostelID",
				"type": "varchar",
				"precision": 0,
				"scale": 0
			},
			{
				"name": "RoomsBooked",
				"type": "int",
				"precision": 10,
				"scale": 0
			}
		],
		"typeProperties": {
			"schema": "dbo",
			"table": "bookingData"
		}
	}
}